atmoswing_toolbox/__init__.py
atmoswing_toolbox/datasets/__init__.py
atmoswing_toolbox/datasets/generic_dataset.py
atmoswing_toolbox/datasets/grib_dataset.py
atmoswing_toolbox/datasets/netcdf_dataset.py
atmoswing_toolbox/datasets/predictor_dataset.py
atmoswing_toolbox/parsers/__init__.py
atmoswing_toolbox/parsers/forecast.py
atmoswing_toolbox/parsers/optimized_parameters.py
atmoswing_toolbox/plots/__init__.py
atmoswing_toolbox/plots/forecast_timeseries.py
atmoswing_toolbox/plots/gas_variables.py
atmoswing_toolbox/plots/montecarlo.py
atmoswing_toolbox/utils/__init__.py
atmoswing_toolbox/utils/cleanup.py
atmoswing_toolbox/utils/compress.py
atmoswing_toolbox/utils/mjd.py
atmoswing_toolbox-1.3.7.dist-info/LICENSE
atmoswing_toolbox-1.3.7.dist-info/METADATA
atmoswing_toolbox-1.3.7.dist-info/WHEEL
atmoswing_toolbox-1.3.7.dist-info/top_level.txt
atmoswing_toolbox-1.3.7.dist-info/RECORD
