Metadata-Version: 2.1
Name: atmoswing-toolbox
Version: 1.3.7
Summary: Python tools for AtmoSwing
Author: Pascal Horton
Author-email: pascal.horton@giub.unibe
License: MIT
Project-URL: Source Code, https://github.com/atmoswing/atmoswing-python-toolbox
Project-URL: Bug Tracker, https://github.com/atmoswing/atmoswing-python-toolbox/issues
Classifier: Programming Language :: Python
Classifier: Programming Language :: Python :: 3
Classifier: License :: OSI Approved :: MIT License
Requires-Python: >=3.8
License-File: LICENSE
Provides-Extra: test
Requires-Dist: pytest (>=6.0) ; extra == 'test'
